fmdata/__init__.py
fmdata/cache_iterator.py
fmdata/const.py
fmdata/fmclient.py
fmdata/inputs.py
fmdata/orm.py
fmdata/results.py
fmdata/session_providers.py
fmdata/utils.py
fmdata-0.0.41.dist-info/LICENSE
fmdata-0.0.41.dist-info/METADATA
fmdata-0.0.41.dist-info/WHEEL
fmdata-0.0.41.dist-info/top_level.txt
fmdata-0.0.41.dist-info/RECORD
