Metadata-Version: 2.1
Name: fmdata
Version: 0.0.41
Summary: fmdata is a wrapper around the FileMaker Data API.
Home-page: https://github.com/Fenix22/python-fmdata
Author: Lorenzo De Siena
Author-email: dev.lorenzo.desiena@gmail.com
License: UNKNOWN
Platform: UNKNOWN
Classifier: Programming Language :: Python
Classifier: Programming Language :: Python :: 3.8
Classifier: License :: OSI Approved :: MIT License
Classifier: Operating System :: OS Independent
Requires-Python: >=3.8
Requires-Dist: requests>=2
Requires-Dist: typing-extensions>=3
Requires-Dist: marshmallow>=3
Provides-Extra: cloud
Requires-Dist: pycognito>=0.1.4; extra == "cloud"
